{
    "name": "stuck",
    "title": "jQuery Stuck",
    "description": "A responsive sticky element jQuery plugin.",
    "keywords": [
        "stuck",
        "sticky",
        "jquery"
    ],
    "version": "1.0.2",
    "author": {
        "name": "Alex Taujenis",
        "url": "https://github.com/alextaujenis"
    },
    "maintainers": [
        {
            "name": "Alex Taujenis",
            "url": "https://github.com/alextaujenis"
        }
    ],
    "licenses": [
        {
            "type": "MIT",
            "url": "http://opensource.org/licenses/mit-license.php"
        }
    ],
    "bugs": "https://github.com/alextaujenis/jquery-stuck/issues",
    "homepage": "http://alextaujenis.github.io/jquery-stuck/",
    "docs": "http://alextaujenis.github.io/jquery-stuck/",
    "download": "https://github.com/alextaujenis/jquery-stuck",
    "dependencies": {
        "jquery": ">=1.5"
    }
}